LICENSE
MANIFEST.in
README.md
setup.py
JoshMokuro.egg-info/PKG-INFO
JoshMokuro.egg-info/SOURCES.txt
JoshMokuro.egg-info/dependency_links.txt
JoshMokuro.egg-info/entry_points.txt
JoshMokuro.egg-info/requires.txt
JoshMokuro.egg-info/top_level.txt
mokuro/__init__.py
mokuro/__main__.py
mokuro/cache.py
mokuro/env.py
mokuro/manga_page_ocr.py
mokuro/overlay_generator.py
mokuro/run.py
mokuro/script.js
mokuro/styles.css
mokuro/utils.py
mokuro/assets/panzoom.min.js
mokuro/assets/icons/chevron-left-double-svgrepo-com.svg
mokuro/assets/icons/chevron-left-svgrepo-com.svg
mokuro/assets/icons/chevron-right-double-svgrepo-com.svg
mokuro/assets/icons/chevron-right-svgrepo-com.svg
mokuro/assets/icons/cross-svgrepo-com.svg
mokuro/assets/icons/expand-svgrepo-com.svg
mokuro/assets/icons/expand-width-svgrepo-com.svg
mokuro/assets/icons/fullscreen-svgrepo-com.svg
mokuro/assets/icons/menu-hamburger-svgrepo-com.svg
tests/__init__.py
tests/generate_expected_results.py
tests/test_mokuro.py