Metadata-Version: 2.1
Name: JoshMokuro
Version: 0.2
Summary: Browser reader for manga with selectable text
Home-page: https://github.com/kha-white/mokuro
Author: Maciej Budyś
Author-email: kha-white@mail.com
License: GPLv3
Classifier: Programming Language :: Python :: 3
License-File: LICENSE
